{
    "key": "group_643e0aa85c2ef",
    "title": "Flex Layouts",
    "fields": [
        {
            "key": "field_643e0aa9a3de0",
            "label": "Flex Layouts",
            "name": "flex_layouts",
            "aria-label": "",
            "type": "flexible_content",
            "instructions": "",
            "required": 0,
            "conditional_logic": 0,
            "wrapper": {
                "width": "",
                "class": "",
                "id": ""
            },
            "layouts": {
                "layout_643e0b117895f": {
                    "key": "layout_643e0b117895f",
                    "name": "hero",
                    "label": "Hero",
                    "display": "block",
                    "sub_fields": [
                        {
                            "key": "field_6443773a7acbc",
                            "label": "Content",
                            "name": "",
                            "aria-label": "",
                            "type": "tab",
                            "instructions": "",
                            "required": 0,
                            "conditional_logic": 0,
                            "wrapper": {
                                "width": "",
                                "class": "",
                                "id": ""
                            },
                            "placement": "top",
                            "endpoint": 0
                        },
                        {
                            "key": "field_643e0b69a3de1",
                            "label": "Image",
                            "name": "image",
                            "aria-label": "",
                            "type": "image",
                            "instructions": "",
                            "required": 0,
                            "conditional_logic": 0,
                            "wrapper": {
                                "width": "",
                                "class": "",
                                "id": ""
                            },
                            "return_format": "id",
                            "library": "all",
                            "min_width": "",
                            "min_height": "",
                            "min_size": "",
                            "max_width": "",
                            "max_height": "",
                            "max_size": "",
                            "mime_types": "",
                            "preview_size": "flex-hero"
                        },
                        {
                            "key": "field_64438225d98b0",
                            "label": "Settings",
                            "name": "",
                            "aria-label": "",
                            "type": "tab",
                            "instructions": "",
                            "required": 0,
                            "conditional_logic": 0,
                            "wrapper": {
                                "width": "",
                                "class": "",
                                "id": ""
                            },
                            "placement": "top",
                            "endpoint": 0
                        },
                        {
                            "key": "field_644f04259c4b2",
                            "label": "Settings",
                            "name": "settings",
                            "aria-label": "",
                            "type": "group",
                            "instructions": "",
                            "required": 0,
                            "conditional_logic": 0,
                            "wrapper": {
                                "width": "",
                                "class": "",
                                "id": ""
                            },
                            "layout": "block",
                            "sub_fields": [
                                {
                                    "key": "field_644590e590951",
                                    "label": "Image Settings",
                                    "name": "image_settings_clone",
                                    "aria-label": "",
                                    "type": "clone",
                                    "instructions": "",
                                    "required": 0,
                                    "conditional_logic": 0,
                                    "wrapper": {
                                        "width": "",
                                        "class": "",
                                        "id": ""
                                    },
                                    "clone": [
                                        "field_644586fd71de0"
                                    ],
                                    "display": "seamless",
                                    "layout": "block",
                                    "prefix_label": 0,
                                    "prefix_name": 0
                                }
                            ]
                        }
                    ],
                    "min": "",
                    "max": ""
                },
                "layout_644570929637f": {
                    "key": "layout_644570929637f",
                    "name": "basic_content",
                    "label": "Basic Content",
                    "display": "block",
                    "sub_fields": [
                        {
                            "key": "field_64456de6cbd73",
                            "label": "Content",
                            "name": "",
                            "aria-label": "",
                            "type": "tab",
                            "instructions": "",
                            "required": 0,
                            "conditional_logic": 0,
                            "wrapper": {
                                "width": "",
                                "class": "",
                                "id": ""
                            },
                            "placement": "top",
                            "endpoint": 0
                        },
                        {
                            "key": "field_64456d05d539a",
                            "label": "Text Content",
                            "name": "text_content",
                            "aria-label": "",
                            "type": "textarea",
                            "instructions": "",
                            "required": 0,
                            "conditional_logic": 0,
                            "wrapper": {
                                "width": "",
                                "class": "",
                                "id": ""
                            },
                            "default_value": "",
                            "maxlength": "",
                            "rows": 6,
                            "placeholder": "",
                            "new_lines": "br"
                        },
                        {
                            "key": "field_64456df3cbd74",
                            "label": "Settings",
                            "name": "",
                            "aria-label": "",
                            "type": "tab",
                            "instructions": "",
                            "required": 0,
                            "conditional_logic": 0,
                            "wrapper": {
                                "width": "",
                                "class": "",
                                "id": ""
                            },
                            "placement": "top",
                            "endpoint": 0
                        },
                        {
                            "key": "field_644598cb5f568",
                            "label": "Settings",
                            "name": "settings",
                            "aria-label": "",
                            "type": "group",
                            "instructions": "",
                            "required": 0,
                            "conditional_logic": 0,
                            "wrapper": {
                                "width": "",
                                "class": "",
                                "id": ""
                            },
                            "layout": "block",
                            "sub_fields": [
                                {
                                    "key": "field_644597c3bfe33",
                                    "label": "Colors",
                                    "name": "",
                                    "aria-label": "",
                                    "type": "tab",
                                    "instructions": "",
                                    "required": 0,
                                    "conditional_logic": 0,
                                    "wrapper": {
                                        "width": "",
                                        "class": "",
                                        "id": ""
                                    },
                                    "placement": "left",
                                    "endpoint": 0
                                },
                                {
                                    "key": "field_644593340f3d0",
                                    "label": "Color Settings",
                                    "name": "color_settings_clone",
                                    "aria-label": "",
                                    "type": "clone",
                                    "instructions": "",
                                    "required": 0,
                                    "conditional_logic": 0,
                                    "wrapper": {
                                        "width": "",
                                        "class": "",
                                        "id": ""
                                    },
                                    "clone": [
                                        "field_6445860c6d0c5"
                                    ],
                                    "display": "seamless",
                                    "layout": "block",
                                    "prefix_label": 0,
                                    "prefix_name": 0
                                },
                                {
                                    "key": "field_644597e1bfe34",
                                    "label": "Spacing",
                                    "name": "",
                                    "aria-label": "",
                                    "type": "tab",
                                    "instructions": "",
                                    "required": 0,
                                    "conditional_logic": 0,
                                    "wrapper": {
                                        "width": "",
                                        "class": "",
                                        "id": ""
                                    },
                                    "placement": "left",
                                    "endpoint": 0
                                },
                                {
                                    "key": "field_644596cf20fdb",
                                    "label": "Spacing Settings",
                                    "name": "spacing_settings_clone",
                                    "aria-label": "",
                                    "type": "clone",
                                    "instructions": "",
                                    "required": 0,
                                    "conditional_logic": 0,
                                    "wrapper": {
                                        "width": "",
                                        "class": "",
                                        "id": ""
                                    },
                                    "clone": [
                                        "field_6445861c6d0c8"
                                    ],
                                    "display": "seamless",
                                    "layout": "block",
                                    "prefix_label": 0,
                                    "prefix_name": 0
                                },
                                {
                                    "key": "field_644663623b3fa",
                                    "label": "Layout",
                                    "name": "",
                                    "aria-label": "",
                                    "type": "tab",
                                    "instructions": "",
                                    "required": 0,
                                    "conditional_logic": 0,
                                    "wrapper": {
                                        "width": "",
                                        "class": "",
                                        "id": ""
                                    },
                                    "placement": "left",
                                    "endpoint": 0
                                },
                                {
                                    "key": "field_6446636f3b3fb",
                                    "label": "Layout Settings",
                                    "name": "layout_settings_clone",
                                    "aria-label": "",
                                    "type": "clone",
                                    "instructions": "",
                                    "required": 0,
                                    "conditional_logic": 0,
                                    "wrapper": {
                                        "width": "",
                                        "class": "",
                                        "id": ""
                                    },
                                    "clone": [
                                        "field_6445996edcd4c"
                                    ],
                                    "display": "seamless",
                                    "layout": "block",
                                    "prefix_label": 0,
                                    "prefix_name": 0
                                }
                            ]
                        }
                    ],
                    "min": "",
                    "max": ""
                },
                "layout_643e117a661ed": {
                    "key": "layout_643e117a661ed",
                    "name": "advanced_content",
                    "label": "Advanced Content",
                    "display": "block",
                    "sub_fields": [
                        {
                            "key": "field_644381015d7c5",
                            "label": "Content",
                            "name": "",
                            "aria-label": "",
                            "type": "tab",
                            "instructions": "",
                            "required": 0,
                            "conditional_logic": 0,
                            "wrapper": {
                                "width": "",
                                "class": "",
                                "id": ""
                            },
                            "placement": "top",
                            "endpoint": 0
                        },
                        {
                            "key": "field_64456dfbcbd75",
                            "label": "Visual Editor",
                            "name": "visual_editor",
                            "aria-label": "",
                            "type": "wysiwyg",
                            "instructions": "",
                            "required": 0,
                            "conditional_logic": 0,
                            "wrapper": {
                                "width": "",
                                "class": "",
                                "id": ""
                            },
                            "default_value": "",
                            "tabs": "all",
                            "toolbar": "full",
                            "media_upload": 1,
                            "delay": 1
                        },
                        {
                            "key": "field_6443810b5d7c6",
                            "label": "Settings",
                            "name": "",
                            "aria-label": "",
                            "type": "tab",
                            "instructions": "",
                            "required": 0,
                            "conditional_logic": 0,
                            "wrapper": {
                                "width": "",
                                "class": "",
                                "id": ""
                            },
                            "placement": "top",
                            "endpoint": 0
                        },
                        {
                            "key": "field_644662fd3b3f6",
                            "label": "Settings",
                            "name": "settings",
                            "aria-label": "",
                            "type": "group",
                            "instructions": "",
                            "required": 0,
                            "conditional_logic": 0,
                            "wrapper": {
                                "width": "",
                                "class": "",
                                "id": ""
                            },
                            "layout": "block",
                            "sub_fields": [
                                {
                                    "key": "field_644663353b3f8",
                                    "label": "Spacing",
                                    "name": "",
                                    "aria-label": "",
                                    "type": "tab",
                                    "instructions": "",
                                    "required": 0,
                                    "conditional_logic": 0,
                                    "wrapper": {
                                        "width": "",
                                        "class": "",
                                        "id": ""
                                    },
                                    "placement": "left",
                                    "endpoint": 0
                                },
                                {
                                    "key": "field_6446628ee6d26",
                                    "label": "Spacing Settings",
                                    "name": "spacing_settings_clone",
                                    "aria-label": "",
                                    "type": "clone",
                                    "instructions": "",
                                    "required": 0,
                                    "conditional_logic": 0,
                                    "wrapper": {
                                        "width": "",
                                        "class": "",
                                        "id": ""
                                    },
                                    "clone": [
                                        "field_6445861c6d0c8"
                                    ],
                                    "display": "seamless",
                                    "layout": "block",
                                    "prefix_label": 0,
                                    "prefix_name": 0
                                },
                                {
                                    "key": "field_644663473b3f9",
                                    "label": "Layout",
                                    "name": "",
                                    "aria-label": "",
                                    "type": "tab",
                                    "instructions": "",
                                    "required": 0,
                                    "conditional_logic": 0,
                                    "wrapper": {
                                        "width": "",
                                        "class": "",
                                        "id": ""
                                    },
                                    "placement": "left",
                                    "endpoint": 0
                                },
                                {
                                    "key": "field_644663103b3f7",
                                    "label": "Layout Settings",
                                    "name": "layout_settings_clone",
                                    "aria-label": "",
                                    "type": "clone",
                                    "instructions": "",
                                    "required": 0,
                                    "conditional_logic": 0,
                                    "wrapper": {
                                        "width": "",
                                        "class": "",
                                        "id": ""
                                    },
                                    "clone": [
                                        "field_6445996edcd4c"
                                    ],
                                    "display": "seamless",
                                    "layout": "block",
                                    "prefix_label": 0,
                                    "prefix_name": 0
                                }
                            ]
                        }
                    ],
                    "min": "",
                    "max": ""
                },
                "layout_64436ed97acb7": {
                    "key": "layout_64436ed97acb7",
                    "name": "section_heading",
                    "label": "Section Heading",
                    "display": "block",
                    "sub_fields": [
                        {
                            "key": "field_64436ee97acb9",
                            "label": "Content",
                            "name": "",
                            "aria-label": "",
                            "type": "tab",
                            "instructions": "",
                            "required": 0,
                            "conditional_logic": 0,
                            "wrapper": {
                                "width": "",
                                "class": "",
                                "id": ""
                            },
                            "placement": "top",
                            "endpoint": 0
                        },
                        {
                            "key": "field_6443814a36b34",
                            "label": "Heading",
                            "name": "heading",
                            "aria-label": "",
                            "type": "group",
                            "instructions": "",
                            "required": 0,
                            "conditional_logic": 0,
                            "wrapper": {
                                "width": "",
                                "class": "",
                                "id": ""
                            },
                            "layout": "table",
                            "sub_fields": [
                                {
                                    "key": "field_6443816936b35",
                                    "label": "Text",
                                    "name": "text",
                                    "aria-label": "",
                                    "type": "text",
                                    "instructions": "",
                                    "required": 0,
                                    "conditional_logic": 0,
                                    "wrapper": {
                                        "width": "85",
                                        "class": "",
                                        "id": ""
                                    },
                                    "default_value": "",
                                    "maxlength": "",
                                    "placeholder": "",
                                    "prepend": "",
                                    "append": ""
                                },
                                {
                                    "key": "field_6443817436b36",
                                    "label": "Heading Tag",
                                    "name": "heading_tag",
                                    "aria-label": "",
                                    "type": "select",
                                    "instructions": "",
                                    "required": 0,
                                    "conditional_logic": 0,
                                    "wrapper": {
                                        "width": "15",
                                        "class": "",
                                        "id": ""
                                    },
                                    "choices": {
                                        "h1": "h1",
                                        "h2": "h2",
                                        "h3": "h3",
                                        "h4": "h4",
                                        "h5": "h5",
                                        "h6": "h6"
                                    },
                                    "default_value": "h2",
                                    "return_format": "value",
                                    "multiple": 0,
                                    "allow_null": 0,
                                    "ui": 0,
                                    "ajax": 0,
                                    "placeholder": ""
                                }
                            ]
                        },
                        {
                            "key": "field_64436ef47acba",
                            "label": "Settings",
                            "name": "",
                            "aria-label": "",
                            "type": "tab",
                            "instructions": "",
                            "required": 0,
                            "conditional_logic": 0,
                            "wrapper": {
                                "width": "",
                                "class": "",
                                "id": ""
                            },
                            "placement": "top",
                            "endpoint": 0
                        },
                        {
                            "key": "field_64439fdc52fde",
                            "label": "Settings",
                            "name": "settings",
                            "aria-label": "",
                            "type": "group",
                            "instructions": "",
                            "required": 0,
                            "conditional_logic": 0,
                            "wrapper": {
                                "width": "",
                                "class": "",
                                "id": ""
                            },
                            "layout": "block",
                            "sub_fields": [
                                {
                                    "key": "field_644663c415607",
                                    "label": "Spacing",
                                    "name": "",
                                    "aria-label": "",
                                    "type": "tab",
                                    "instructions": "",
                                    "required": 0,
                                    "conditional_logic": 0,
                                    "wrapper": {
                                        "width": "",
                                        "class": "",
                                        "id": ""
                                    },
                                    "placement": "left",
                                    "endpoint": 0
                                },
                                {
                                    "key": "field_6446641c15609",
                                    "label": "Spacing Settings",
                                    "name": "spacing_settings_clone",
                                    "aria-label": "",
                                    "type": "clone",
                                    "instructions": "",
                                    "required": 0,
                                    "conditional_logic": 0,
                                    "wrapper": {
                                        "width": "",
                                        "class": "",
                                        "id": ""
                                    },
                                    "clone": [
                                        "field_6445861c6d0c8"
                                    ],
                                    "display": "seamless",
                                    "layout": "block",
                                    "prefix_label": 0,
                                    "prefix_name": 0
                                },
                                {
                                    "key": "field_6446640f15608",
                                    "label": "Layout",
                                    "name": "",
                                    "aria-label": "",
                                    "type": "tab",
                                    "instructions": "",
                                    "required": 0,
                                    "conditional_logic": 0,
                                    "wrapper": {
                                        "width": "",
                                        "class": "",
                                        "id": ""
                                    },
                                    "placement": "left",
                                    "endpoint": 0
                                },
                                {
                                    "key": "field_644664391560a",
                                    "label": "Layout Settings",
                                    "name": "layout_settings_clone",
                                    "aria-label": "",
                                    "type": "clone",
                                    "instructions": "",
                                    "required": 0,
                                    "conditional_logic": 0,
                                    "wrapper": {
                                        "width": "",
                                        "class": "",
                                        "id": ""
                                    },
                                    "clone": [
                                        "field_6445996edcd4c"
                                    ],
                                    "display": "seamless",
                                    "layout": "block",
                                    "prefix_label": 0,
                                    "prefix_name": 0
                                }
                            ]
                        }
                    ],
                    "min": "",
                    "max": ""
                }
            },
            "min": "",
            "max": "",
            "button_label": "Add Layout"
        }
    ],
    "location": [
        [
            {
                "param": "post_template",
                "operator": "==",
                "value": "templates\/flexible-content.php"
            }
        ]
    ],
    "menu_order": 0,
    "position": "normal",
    "style": "seamless",
    "label_placement": "top",
    "instruction_placement": "label",
    "hide_on_screen": [
        "the_content",
        "featured_image"
    ],
    "active": true,
    "description": "",
    "show_in_rest": 0,
    "modified": 1682902537
}